TextFormatConverter/__init__.py
TextFormatConverter/json_to_md.py
TextFormatConverter/md_to_json.py
text_format_converter-0.23.dist-info/LICENSE
text_format_converter-0.23.dist-info/METADATA
text_format_converter-0.23.dist-info/WHEEL
text_format_converter-0.23.dist-info/top_level.txt
text_format_converter-0.23.dist-info/RECORD
