Metadata-Version: 2.1
Name: text-format-converter
Version: 0.23
Summary: text format converter
Home-page: https://github.com/dataran/TextFormatConverter
Author: Ran Geler
Author-email: geler.ran@gmail.com
Classifier: Programming Language :: Python :: 3
Classifier: Operating System :: OS Independent
Requires-Python: >=3.8
License-File: LICENSE
Provides-Extra: dev
Requires-Dist: pytest>=0.7; extra == "dev"
Requires-Dist: twine>=6.0.1; extra == "dev"
